mathPkg/__init__.py
mathPkg/mathPkg.py
mathPkg-0.0.2.dist-info/LICENSE
mathPkg-0.0.2.dist-info/METADATA
mathPkg-0.0.2.dist-info/WHEEL
mathPkg-0.0.2.dist-info/top_level.txt
mathPkg-0.0.2.dist-info/RECORD
