Metadata-Version: 2.1
Name: mathPkg
Version: 0.0.2
Summary: A pakage that contains some math functions
Author-email: Jameel Ahamd <msdsf22m013@pucit.edu.pk>
Project-URL: Homepage, https://github.com/MSDSF22M013/MSDS_TTFDS_A1
Project-URL: Bug Tracker, https://github.com/MSDSF22M013/MSDS_TTFDS_A1/issues
Classifier: Programming Language :: Python :: 3
Classifier: License :: OSI Approved :: MIT License
Classifier: Operating System :: OS Independent
Requires-Python: >=3.7
License-File: LICENSE
